pycomptox/__init__.py
pycomptox/apis/__init__.py
pycomptox/apis/bioactivity.py
pycomptox/apis/chem_details.py
pycomptox/apis/chem_search.py
pycomptox/apis/exposure.py
pycomptox/apis/hazard.py
pycomptox/core/__init__.py
pycomptox/core/base_client.py
pycomptox/core/config.py
pycomptox/utils/__init__.py
pycomptox/utils/exceptions.py
pycomptox/utils/logging_utils.py
pycomptox-0.1.2.dist-info/LICENSE
pycomptox-0.1.2.dist-info/METADATA
pycomptox-0.1.2.dist-info/WHEEL
pycomptox-0.1.2.dist-info/top_level.txt
pycomptox-0.1.2.dist-info/RECORD
