Metadata-Version: 2.1
Name: pycomptox
Version: 0.1.2
Summary: This is a lightweight wrapper for comptox APIs (for computational toxicology)
Author-email: Kunal Chandra <your.email@example.com>
Maintainer-email: Kunal Chandra <your.email@example.com>
License: MIT License
Project-URL: homepage, https://github.com/Kunal627/pycomptox
Project-URL: bug_tracker, https://github.com/Kunal627/pycomptox/issues
Project-URL: documentation, https://github.com/Kunal627/pycomptox/blob/main/README.md
Project-URL: repository, https://github.com/Kunal627/pycomptox
Keywords: API,wrapper,REST,comptox,toxicology,computational
Classifier: Development Status :: 4 - Beta
Classifier: Intended Audience :: Developers
Classifier: Programming Language :: Python :: 3.9
Classifier: License :: OSI Approved :: MIT License
Requires-Python: >=3.9
License-File: LICENSE
Requires-Dist: requests
